laraflask/__init__.py
laraflask/__main__.py
laraflask/core.py
laraflask/Helpers/__init__.py
laraflask/Helpers/config.py
laraflask/Routes/__init__.py
laraflask/Routes/assets.py
laraflask-0.26.dist-info/LICENSE
laraflask-0.26.dist-info/METADATA
laraflask-0.26.dist-info/WHEEL
laraflask-0.26.dist-info/entry_points.txt
laraflask-0.26.dist-info/top_level.txt
laraflask-0.26.dist-info/RECORD
